Metadata-Version: 2.4
Name: semantic-copycat-binarysniffer
Version: 1.11.1
Summary: A high-performance CLI and library for detecting open source components in binaries through semantic signature matching
Author-email: "Oscar Valenzuela B." <oscar.valenzuela.b@gmail.com>
License: Apache-2.0
Project-URL: Homepage, https://github.com/oscarvalenzuelab/semantic-copycat-binarysniffer
Project-URL: Bug Tracker, https://github.com/oscarvalenzuelab/semantic-copycat-binarysniffer/issues
Project-URL: Documentation, https://github.com/oscarvalenzuelab/semantic-copycat-binarysniffer/tree/main/docs
Keywords: binary-analysis,license-compliance,signature-matching,oss-detection,semantic-analysis,semantic-copycat,code-copycat
Classifier: Development Status :: 4 - Beta
Classifier: Environment :: Console
Classifier: Intended Audience :: Developers
Classifier: Intended Audience :: System Administrators
Classifier: License :: OSI Approved :: Apache Software License
Classifier: Operating System :: OS Independent
Classifier: Programming Language :: Python :: 3
Classifier: Programming Language :: Python :: 3.8
Classifier: Programming Language :: Python :: 3.9
Classifier: Programming Language :: Python :: 3.10
Classifier: Programming Language :: Python :: 3.11
Classifier: Programming Language :: Python :: 3.12
Classifier: Topic :: Security
Classifier: Topic :: Software Development :: Libraries :: Python Modules
Classifier: Topic :: System :: Software Distribution
Requires-Python: >=3.8
License-File: LICENSE
Requires-Dist: click>=8.1.0
Requires-Dist: tqdm>=4.66.0
Requires-Dist: xxhash>=3.5.0
Requires-Dist: zstandard>=0.23.0
Requires-Dist: pybloom-live>=4.0.0
Requires-Dist: python-magic>=0.4.27
Requires-Dist: pygments>=2.18.0
Requires-Dist: rich>=13.0.0
Requires-Dist: tabulate>=0.9.0
Requires-Dist: semantic-copycat-oslili>=1.5.0
Requires-Dist: semantic-copycat-upmex>=1.6.2
Provides-Extra: fuzzy
Requires-Dist: python-tlsh>=4.5.0; extra == "fuzzy"
Provides-Extra: android
Requires-Dist: androguard>=4.1.0; extra == "android"
Provides-Extra: archives
Requires-Dist: py7zr>=0.21.0; extra == "archives"
Requires-Dist: rarfile>=4.2; extra == "archives"
Requires-Dist: python-debian>=0.1.49; extra == "archives"
Provides-Extra: dev
Requires-Dist: pytest>=8.0.0; extra == "dev"
Requires-Dist: pytest-cov>=5.0.0; extra == "dev"
Requires-Dist: black>=24.0.0; extra == "dev"
Requires-Dist: mypy>=1.8.0; extra == "dev"
Requires-Dist: ruff>=0.3.0; extra == "dev"
Requires-Dist: pre-commit>=3.6.0; extra == "dev"
Provides-Extra: fast
Requires-Dist: lz4>=4.3.0; extra == "fast"
Requires-Dist: numpy>=1.24.0; extra == "fast"
Requires-Dist: scikit-learn>=1.4.0; extra == "fast"
Dynamic: license-file
